LICENSE.txt
MANIFEST.in
Readme.md
setup.py
hvac_ir/__init__.py
hvac_ir/ballu.py
hvac_ir/carriermca.py
hvac_ir/carriernqv.py
hvac_ir/daikin.py
hvac_ir/daikin2.py
hvac_ir/fuego.py
hvac_ir/fujitsu.py
hvac_ir/gree.py
hvac_ir/hisense.py
hvac_ir/hitachi.py
hvac_ir/hyundai.py
hvac_ir/midea.py
hvac_ir/mitsubishi.py
hvac_ir.egg-info/PKG-INFO
hvac_ir.egg-info/SOURCES.txt
hvac_ir.egg-info/dependency_links.txt
hvac_ir.egg-info/not-zip-safe
hvac_ir.egg-info/top_level.txt