Metadata-Version: 1.1
Name: hvac-ir
Version: 0.7
Summary: Air conditioner control code generator
Home-page: http://github.com/shprota/hvac_ir
Author: Shprota
Author-email: shprota@gmail.com
License: MIT
Keywords: airconditioner hvac ac control ir infrared heatpump midea gree daikin carrier
Platform: UNKNOWN
Classifier: Development Status :: 3 - Alpha
Classifier: Intended Audience :: Developers
Classifier: License :: OSI Approved :: MIT License
Classifier: Programming Language :: Python :: 2.7
Classifier: Programming Language :: Python :: 3
Classifier: Programming Language :: Python :: 3.2
Classifier: Programming Language :: Python :: 3.3
Classifier: Programming Language :: Python :: 3.4
Classifier: Programming Language :: Python :: 3.5
Classifier: Programming Language :: Python :: 3.6
Classifier: Programming Language :: Python :: 3.7
